route53weightedrecords/__init__.py
route53weightedrecords-0.4.dist-info/METADATA
route53weightedrecords-0.4.dist-info/RECORD
route53weightedrecords-0.4.dist-info/WHEEL
route53weightedrecords-0.4.dist-info/top_level.txt
